MANIFEST
MANIFEST.in
setup.py
docs/fluid.pdf
fluid/DataSet.py
fluid/README.fluid
fluid/__init__.py
fluid/coards.py
fluid/dtypes.py
fluid/io.py
fluid/magic.py
fluid/test.py
fluid/turb_HF.py
fluid.egg-info/PKG-INFO
fluid.egg-info/SOURCES.txt
fluid.egg-info/dependency_links.txt
fluid.egg-info/top_level.txt
fluid/atmosphere/__init__.py
fluid/atmosphere/atmospheric_constants.py
fluid/atmosphere/atmospheric_functions.py
fluid/common/__init__.py
fluid/common/common.py
fluid/common/distance.py
fluid/common/gfd.py
fluid/common/window_mean.py
fluid/interaction/__init__.py
fluid/interaction/estuary.py
fluid/interaction/heat_flux.py
fluid/interaction/interaction_constants.py
fluid/interaction/others.py
fluid/ocean/__init__.py
fluid/ocean/estuary.py
fluid/ocean/rings.py
fluid/ocean/seawater.py
