Metadata-Version: 1.0
Name: fluid
Version: 0.1.6
Summary: Procedures to study geophysical fluids on Python.
Home-page: http://fluid.oceanografia.org/
Author: Guilherme Castelao and Roberto de Almeida
Author-email: guilherme@castelao.net
License: MIT
Download-URL: http://cheeseshop.python.org/packages/source/f/fluid/fluid-0.1.5.tar.gz
Keywords: fluid oceanography meteorology seawater heat flux wind
Platform: any
Classifier: Development Status :: 4 - Beta
Classifier: Environment :: Console
Classifier: Intended Audience :: Science/Research
Classifier: Intended Audience :: Developers
Classifier: Intended Audience :: Education
Classifier: License :: OSI Approved :: MIT License 
Classifier: Operating System :: OS Independent
Classifier: Programming Language :: Python
Classifier: Topic :: Scientific/Engineering
Classifier: Topic :: Education
Classifier: Topic :: Software Development :: Libraries :: Python Modules
